vital/__init__.py
vital/activity/__init__.py
vital/activity/client.py
vital/activity/raw_client.py
vital/aggregate/__init__.py
vital/aggregate/client.py
vital/aggregate/raw_client.py
vital/aggregate/types/__init__.py
vital/aggregate/types/query_batch_timeframe.py
vital/body/__init__.py
vital/body/client.py
vital/body/raw_client.py
vital/client.py
vital/core/__init__.py
vital/core/api_error.py
vital/core/client_wrapper.py
vital/core/datetime_utils.py
vital/core/file.py
vital/core/http_client.py
vital/core/http_response.py
vital/core/jsonable_encoder.py
vital/core/pydantic_utilities.py
vital/core/query_encoder.py
vital/core/remove_none_from_dict.py
vital/core/request_options.py
vital/core/serialization.py
vital/devices/__init__.py
vital/devices/client.py
vital/devices/raw_client.py
vital/electrocardiogram/__init__.py
vital/electrocardiogram/client.py
vital/electrocardiogram/raw_client.py
vital/environment.py
vital/errors/__init__.py
vital/errors/bad_request_error.py
vital/errors/not_found_error.py
vital/errors/unprocessable_entity_error.py
vital/insurance/__init__.py
vital/insurance/client.py
vital/insurance/raw_client.py
vital/introspect/__init__.py
vital/introspect/client.py
vital/introspect/raw_client.py
vital/introspect/types/__init__.py
vital/introspect/types/get_user_historical_pulls_introspect_request_provider.py
vital/lab_report/__init__.py
vital/lab_report/client.py
vital/lab_report/raw_client.py
vital/lab_tests/__init__.py
vital/lab_tests/client.py
vital/lab_tests/raw_client.py
vital/lab_tests/types/__init__.py
vital/lab_tests/types/get_lab_tests_request_order_direction.py
vital/lab_tests/types/get_lab_tests_request_order_key.py
vital/lab_tests/types/get_orders_lab_tests_request_order_direction.py
vital/lab_tests/types/get_orders_lab_tests_request_order_key.py
vital/lab_tests/types/get_paginated_lab_tests_request_order_direction.py
vital/lab_tests/types/get_paginated_lab_tests_request_order_key.py
vital/link/__init__.py
vital/link/client.py
vital-2.1.560.dist-info/METADATA
vital-2.1.560.dist-info/WHEEL
vital-2.1.560.dist-info/RECORD
